<?xml version="1.0" ?><annotation>
	<folder>images</folder>
	<filename>000105.xml</filename>
	<path>F:\Graduate student - Research - Thesis\Chapter Two - Helmet detection in complex scenarios\datasets\rename-image\000105.xml</path>
	<source>
		<database>Unknown</database>
	</source>
	<size>
		<width>600</width>
		<height>399</height>
		<depth>3</depth>
	</size>
	<segmented>0</segmented>
	<object>
		<name>head</name>
		<pose>Unspecified</pose>
		<truncated>0</truncated>
		<difficult>0</difficult>
		<bndbox>
			<xmin>489</xmin>
			<ymin>284</ymin>
			<xmax>530</xmax>
			<ymax>344</ymax>
		</bndbox>
	</object>
	<object>
		<name>head</name>
		<pose>Unspecified</pose>
		<truncated>0</truncated>
		<difficult>0</difficult>
		<bndbox>
			<xmin>417</xmin>
			<ymin>265</ymin>
			<xmax>494</xmax>
			<ymax>360</ymax>
		</bndbox>
	</object>
	<object>
		<name>helmet</name>
		<pose>Unspecified</pose>
		<truncated>0</truncated>
		<difficult>0</difficult>
		<bndbox>
			<xmin>172</xmin>
			<ymin>265</ymin>
			<xmax>248</xmax>
			<ymax>362</ymax>
		</bndbox>
	</object>
	<object>
		<name>head</name>
		<pose>Unspecified</pose>
		<truncated>0</truncated>
		<difficult>0</difficult>
		<bndbox>
			<xmin>41</xmin>
			<ymin>270</ymin>
			<xmax>82</xmax>
			<ymax>320</ymax>
		</bndbox>
	</object>
</annotation>