<annotation>
	<folder>Images</folder>
	<filename>000377.jpg</filename>
	<path>F:\Graduate student - Research - Thesis\Chapter Two - Helmet detection in complex scenarios\VOCdevkit\Images\000377.jpg</path>
	<source>
		<database>Unknown</database>
	</source>
	<size>
		<width>721</width>
		<height>1280</height>
		<depth>3</depth>
	</size>
	<segmented>0</segmented>
	<object>
		<name>helmet</name>
		<pose>Unspecified</pose>
		<truncated>0</truncated>
		<difficult>0</difficult>
		<bndbox>
			<xmin>40</xmin>
			<ymin>417</ymin>
			<xmax>84</xmax>
			<ymax>457</ymax>
		</bndbox>
	</object>
	<object>
		<name>helmet</name>
		<pose>Unspecified</pose>
		<truncated>0</truncated>
		<difficult>0</difficult>
		<bndbox>
			<xmin>45</xmin>
			<ymin>423</ymin>
			<xmax>151</xmax>
			<ymax>510</ymax>
		</bndbox>
	</object>
	<object>
		<name>head</name>
		<pose>Unspecified</pose>
		<truncated>0</truncated>
		<difficult>0</difficult>
		<bndbox>
			<xmin>113</xmin>
			<ymin>232</ymin>
			<xmax>160</xmax>
			<ymax>271</ymax>
		</bndbox>
	</object>
</annotation>
