<annotation>
	<folder>Images</folder>
	<filename>000354.jpg</filename>
	<path>F:\Graduate student - Research - Thesis\Chapter Two - Helmet detection in complex scenarios\VOCdevkit\Images\000354.jpg</path>
	<source>
		<database>Unknown</database>
	</source>
	<size>
		<width>1920</width>
		<height>1080</height>
		<depth>3</depth>
	</size>
	<segmented>0</segmented>
	<object>
		<name>helmet</name>
		<pose>Unspecified</pose>
		<truncated>0</truncated>
		<difficult>0</difficult>
		<bndbox>
			<xmin>898</xmin>
			<ymin>451</ymin>
			<xmax>1028</xmax>
			<ymax>629</ymax>
		</bndbox>
	</object>
	<object>
		<name>helmet</name>
		<pose>Unspecified</pose>
		<truncated>0</truncated>
		<difficult>0</difficult>
		<bndbox>
			<xmin>1012</xmin>
			<ymin>481</ymin>
			<xmax>1057</xmax>
			<ymax>600</ymax>
		</bndbox>
	</object>
	<object>
		<name>helmet</name>
		<pose>Unspecified</pose>
		<truncated>0</truncated>
		<difficult>0</difficult>
		<bndbox>
			<xmin>735</xmin>
			<ymin>524</ymin>
			<xmax>788</xmax>
			<ymax>618</ymax>
		</bndbox>
	</object>
</annotation>
