<annotation>
	<folder>Images</folder>
	<filename>001485.jpg</filename>
	<path>F:\Graduate student - Research - Thesis\Chapter Two - Helmet detection in complex scenarios\VOCdevkit\Images\001485.jpg</path>
	<source>
		<database>Unknown</database>
	</source>
	<size>
		<width>826</width>
		<height>826</height>
		<depth>3</depth>
	</size>
	<segmented>0</segmented>
	<object>
		<name>helmet</name>
		<pose>Unspecified</pose>
		<truncated>0</truncated>
		<difficult>0</difficult>
		<bndbox>
			<xmin>279</xmin>
			<ymin>378</ymin>
			<xmax>313</xmax>
			<ymax>412</ymax>
		</bndbox>
	</object>
	<object>
		<name>helmet</name>
		<pose>Unspecified</pose>
		<truncated>0</truncated>
		<difficult>0</difficult>
		<bndbox>
			<xmin>215</xmin>
			<ymin>319</ymin>
			<xmax>254</xmax>
			<ymax>353</ymax>
		</bndbox>
	</object>
</annotation>
